image_processing_soek/__init__.py
image_processing_soek/processing/__init__.py
image_processing_soek/processing/combination.py
image_processing_soek/processing/transformation.py
image_processing_soek/utils/__init__.py
image_processing_soek/utils/io.py
image_processing_soek/utils/plot.py
image_processing_soek-0.0.1.dist-info/METADATA
image_processing_soek-0.0.1.dist-info/WHEEL
image_processing_soek-0.0.1.dist-info/top_level.txt
image_processing_soek-0.0.1.dist-info/RECORD
