Metadata-Version: 2.1
Name: image-processing-soek
Version: 0.0.1
Summary: Image Processing Package using Skimage
Home-page: https://gitlab.com/dio-ciencia-de-dados/image-processing
Author: Diego Soek
License: UNKNOWN
Platform: UNKNOWN
Requires-Python: >=3.5
Requires-Dist: matplotlib
Requires-Dist: numpy
Requires-Dist: scikit-image (>=0.16.1)
